phone_homer-0.0.1.data/data/my_data/data_file
phone_homer-0.0.1.dist-info/DESCRIPTION.rst
phone_homer-0.0.1.dist-info/METADATA
phone_homer-0.0.1.dist-info/RECORD
phone_homer-0.0.1.dist-info/WHEEL
phone_homer-0.0.1.dist-info/entry_points.txt
phone_homer-0.0.1.dist-info/metadata.json
phone_homer-0.0.1.dist-info/top_level.txt
sample/__init__.py
sample/package_data.dat
