Metadata-Version: 2.0
Name: phone-homer
Version: 0.0.1
Summary: DO NOT USE THIS MODULE!
Home-page: https://github.com/kitplummer/sampleproject
Author: Kit Plummer
Author-email: kit.plummer@gtri.gatech.edu
License: MIT
Keywords: sample security tools
Platform: UNKNOWN
Classifier: Development Status :: 3 - Alpha
Classifier: Intended Audience :: Developers
Classifier: Topic :: Software Development :: Build Tools
Classifier: License :: OSI Approved :: MIT License
Classifier: Programming Language :: Python :: 3
Classifier: Programming Language :: Python :: 3.3
Classifier: Programming Language :: Python :: 3.4
Classifier: Programming Language :: Python :: 3.5
Classifier: Programming Language :: Python :: 3.6
Requires-Dist: peppercorn
Provides-Extra: dev
Requires-Dist: check-manifest; extra == 'dev'
Provides-Extra: test
Requires-Dist: coverage; extra == 'test'
